[
  {
    "variant_id": "variant_ig_001",
    "content_id": "content_20260508_001",
    "client_id": "client_study_001",
    "platform": "instagram",
    "account_id": "ig_study_001",
    "format": "reel",
    "caption": "很多家长以为转学分只是换学校，其实最容易亏的是这些学分。\n\n想知道你的情况能不能转学分，可以私信我。",
    "hashtags": [
      "#加拿大留学",
      "#转学分",
      "#留学生",
      "#多伦多留学"
    ],
    "media_path": "data/clients/client_study_001/exports/instagram/college_transfer_instagram.mp4",
    "cta": "私信我，帮你判断能不能转。",
    "status": "ready_for_review"
  },
  {
    "variant_id": "variant_tk_001",
    "content_id": "content_20260508_001",
    "client_id": "client_study_001",
    "platform": "tiktok",
    "account_id": "tiktok_study_001",
    "format": "short_video",
    "caption": "加拿大大学转学分，很多家长一开始就搞错了。很多家长以为转学分只是换学校，其实最容易亏的是这些学分。 评论区打关键词，我帮你判断。",
    "hashtags": [
      "#加拿大留学",
      "#转学分",
      "#留学生",
      "#多伦多留学"
    ],
    "media_path": "data/clients/client_study_001/exports/tiktok/college_transfer_tiktok.mp4",
    "cta": "想知道你的情况能不能转，评论区打“转学分”。",
    "status": "ready_for_review"
  },
  {
    "variant_id": "variant_fb_001",
    "content_id": "content_20260508_001",
    "client_id": "client_study_001",
    "platform": "facebook",
    "account_id": "facebook_study_001",
    "format": "page_post",
    "caption": "加拿大大学转学分，很多家长一开始就搞错了\n\n很多家长以为转学分只是换学校，其实最容易亏的是这些学分。\n\n- 不是所有课程都能转\n- 学校之间评估标准不同\n- 专业方向会影响转学分结果\n- 提前规划可以减少时间和学费浪费\n\n想知道你的情况能不能转学分，可以私信我。",
    "hashtags": [
      "#CanadaStudy",
      "#StudyAbroad",
      "#TransferCredit"
    ],
    "media_path": "data/clients/client_study_001/exports/facebook/college_transfer_facebook.mp4",
    "cta": "想知道你的情况能不能转学分，可以私信我。",
    "status": "ready_for_review"
  }
]
